stweet/__init__.py
stweet/auth/__init__.py
stweet/auth/auth_token_provider.py
stweet/auth/fail_strategy/__init__.py
stweet/auth/fail_strategy/auth_fail_strategy.py
stweet/auth/fail_strategy/tor_ip_change_auth_fail_strategy.py
stweet/auth/fail_strategy/wait_auth_fail_strategy.py
stweet/auth/simple_auth_token_provider.py
stweet/exceptions/__init__.py
stweet/exceptions/refresh_token_exception.py
stweet/exceptions/scrap_batch_bad_response.py
stweet/exceptions/too_many_requests_exception.py
stweet/exceptions/user_suspended_exception.py
stweet/get_user_runner/__init__.py
stweet/get_user_runner/get_users_context.py
stweet/get_user_runner/get_users_result.py
stweet/get_user_runner/get_users_runner.py
stweet/get_user_runner/get_users_task.py
stweet/get_user_runner/user_parser.py
stweet/http_request/__init__.py
stweet/http_request/http_method.py
stweet/http_request/interceptor/__init__.py
stweet/http_request/interceptor/logging_requests_web_client_interceptor.py
stweet/http_request/interceptor/params_response_log_web_client_interceptor.py
stweet/http_request/request_details.py
stweet/http_request/request_response.py
stweet/http_request/requests/__init__.py
stweet/http_request/requests/requests_web_client.py
stweet/http_request/requests/requests_web_client_proxy_config.py
stweet/http_request/web_client.py
stweet/model/__init__.py
stweet/model/cursor.py
stweet/model/language.py
stweet/model/raw_data.py
stweet/model/tweet_raw.py
stweet/model/user_raw.py
stweet/model/user_tweet_raw.py
stweet/raw_output/__init__.py
stweet/raw_output/collector_raw_output.py
stweet/raw_output/json_line_file_raw_output.py
stweet/raw_output/print_every_n_raw_output.py
stweet/raw_output/print_first_in_batch_raw_output.py
stweet/raw_output/print_raw_output.py
stweet/raw_output/raw_data_output.py
stweet/search_runner/__init__.py
stweet/search_runner/replies_filter.py
stweet/search_runner/search_run_context.py
stweet/search_runner/search_runner.py
stweet/search_runner/search_tweets_result.py
stweet-2.1.0.dist-info/METADATA
stweet-2.1.0.dist-info/LICENSE
stweet-2.1.0.dist-info/WHEEL
stweet-2.1.0.dist-info/RECORD
