Metadata-Version: 2.1
Name: stweet
Version: 2.1.0
Summary: Package to scrap tweets
License: MIT
Author: Marcin Wątroba
Author-email: markowanga@gmail.com
Requires-Python: >=3.8,<4.0
Classifier: License :: OSI Approved :: MIT License
Classifier: Programming Language :: Python :: 3
Classifier: Programming Language :: Python :: 3.8
Classifier: Programming Language :: Python :: 3.9
Classifier: Programming Language :: Python :: 3.10
Classifier: Programming Language :: Python :: 3.11
Requires-Dist: arrow (>=1.2.0,<2.0.0)
Requires-Dist: pandas (>=1.3.3,<2.0.0)
Requires-Dist: requests (>=2.26.0,<3.0.0)
Requires-Dist: tor-python-easy (>=0.1.2,<0.2.0)
